Metadata-Version: 2.1
Name: drcontrol
Version: 0.14
Summary: Control Denkovi USB Relay Boards
Home-page: UNKNOWN
Author: Sebastian Sjoholm
Author-email: sebastian.sjoholm@gmail.com
License: GPL-3.0
Platform: UNKNOWN
Classifier: Development Status :: 4 - Beta
Classifier: Intended Audience :: Developers
Classifier: Intended Audience :: Information Technology
Classifier: Intended Audience :: System Administrators
Classifier: Intended Audience :: Telecommunications Industry
Classifier: License :: OSI Approved :: GNU General Public License v3 or later (GPLv3+)
Classifier: Operating System :: POSIX
Classifier: Operating System :: MacOS :: MacOS X
Classifier: Operating System :: Unix
Classifier: Topic :: Utilities
Requires-Python: >=3.4
